pipwhip/__init__.py
pipwhip/main.py
pipwhip/utils.py
pipwhip-0.0.3.dist-info/METADATA
pipwhip-0.0.3.dist-info/WHEEL
pipwhip-0.0.3.dist-info/entry_points.txt
pipwhip-0.0.3.dist-info/top_level.txt
pipwhip-0.0.3.dist-info/RECORD
