Metadata-Version: 2.1
Name: pipwhip
Version: 0.0.3
Summary: A tool to automatically upgrade requirements files.
Home-page: https://github.com/ArcLightSlavik
Author: ArcLightSlavik
License: UNKNOWN
Platform: UNKNOWN
Classifier: Programming Language :: Python :: 3
Classifier: Programming Language :: Python :: 3 :: Only
Classifier: Programming Language :: Python :: 3.6
Classifier: Programming Language :: Python :: 3.7
Classifier: Programming Language :: Python :: 3.8
Classifier: Programming Language :: Python :: 3.9
Requires-Python: >=3.6.1
Requires-Dist: click (>=7.1.2)
Requires-Dist: httpx (>=0.16.1)
Provides-Extra: dev
Requires-Dist: pytest (==6.2.4) ; extra == 'dev'
Requires-Dist: pytest-cov (==2.12.1) ; extra == 'dev'
Requires-Dist: pytest-mock (==3.6.1) ; extra == 'dev'
Requires-Dist: mypy (==0.910) ; extra == 'dev'
Requires-Dist: pre-commit (==2.14.0) ; extra == 'dev'
Requires-Dist: types-pkg-resources (==0.1.3) ; extra == 'dev'
